pdf2mp3/__init__.py
pdf2mp3/__main__.py
pdf2mp3/pdf2mp3.py
pdf2mp3-1.0.0.dist-info/licenses/LICENSE
pdf2mp3-1.0.0.dist-info/METADATA
pdf2mp3-1.0.0.dist-info/WHEEL
pdf2mp3-1.0.0.dist-info/entry_points.txt
pdf2mp3-1.0.0.dist-info/top_level.txt
pdf2mp3-1.0.0.dist-info/RECORD
