Metadata-Version: 2.4
Name: pdf2mp3
Version: 1.0.0
Summary: Convert PDFs to MP3 audiobooks using Microsoft Edge neural voices.
Author-email: Raphael Medeiros <pdf2mp3@byraphaelmedeiros.com>
Maintainer-email: Raphael Medeiros <pdf2mp3@byraphaelmedeiros.com>
License: MIT License
Project-URL: Homepage, https://github.com/byraphaelmedeiros/pdf2mp3
Project-URL: Bug Tracker, https://github.com/byraphaelmedeiros/pdf2mp3/issues
Requires-Python: >=3.9
License-File: LICENSE
Requires-Dist: pdfminer.six<20260000,>=20250506
Requires-Dist: edge-tts<8.0.0,>=7.2.3
Requires-Dist: pydub<0.26.0,>=0.25.1
Requires-Dist: tqdm<5.0.0,>=4.67.1
Dynamic: license-file
